{
    "type": "minecraft:smithing_transform",
    "template": {
      "item": "minecraft:netherite_upgrade_smithing_template"
    },
    "base": {
      "item": "minecraft:leather_chestplate"
    },
    "addition": {
      "item": "minecraft:diamond"
    },
    "result": {
      "id": "minecraft:leather_chestplate",
      "count": 1,
      "components": {
        "minecraft:attribute_modifiers": {
          "modifiers": [
            {
              "id": "eden.armor.chestplate_1",
              "type": "minecraft:generic.armor",
              "amount": 8,
              "operation": "add_value",
              "slot": "chest"
            },
            {
              "id": "eden.armortough.chestplate_1",
              "type": "minecraft:generic.armor_toughness",
              "amount": 2,
              "operation": "add_value",
              "slot": "chest"
            }
          ]
        },
        "minecraft:damage": 0,
        "minecraft:max_damage": 528,
        "minecraft:item_name": "{\"fallback\":\"Diamond Infused Leather Tunic\",\"translate\":\"armor.eden.chestplate.infused.diamond\"}",
        "minecraft:dyed_color": {
          "rgb": 51196,
          "show_in_tooltip": false
        }
      }
    }
  }
  