{
    "pools": [
      {
        "rolls": 1,
        "entries": [
          {
            "type": "minecraft:item",
            "name": "minecraft:rabbit_foot",
            "functions": [
              {
                "function": "minecraft:set_count",
                "count": 1
              },
              {
                "function": "minecraft:set_components",
                "components": {
                  "minecraft:item_name": "{\"fallback\":\"Maki Roll\",\"translate\":\"food.eden.maki_roll\"}",
        "minecraft:custom_model_data": 10016,
        "minecraft:custom_data": "{food:maki_roll}",
        "minecraft:food": {
          "nutrition": 4,
          "saturation": 3,
          "eat_seconds": 2
        }
      }
              }
            ]
          }
        ]
      }
    ]
  }
  